[
 {
  "description": "Pseudorandom test for VFCMADDCSH",
  "id": "vfcmaddcsh16",
  "format": "bin",
  "source": "vfcmaddcsh_narrow.asm",
  "option": "--bits 16 -w-ea-absolute -w-implicit-abs-deprecated -I./travis/insns/vfcmaddcsh/",
  "target": [
   { "output": "vfcmaddcsh.bin16", "match": "vfcmaddcsh.bin16.t" }
  ]
 }
,
 {
  "description": "Pseudorandom test for VFCMADDCSH",
  "id": "vfcmaddcsh32",
  "format": "bin",
  "source": "vfcmaddcsh_narrow.asm",
  "option": "--bits 32 -w-ea-absolute -w-implicit-abs-deprecated -I./travis/insns/vfcmaddcsh/",
  "target": [
   { "output": "vfcmaddcsh.bin32", "match": "vfcmaddcsh.bin32.t" }
  ]
 }
,
 {
  "description": "Pseudorandom test for VFCMADDCSH",
  "id": "vfcmaddcsh64",
  "format": "bin",
  "source": "vfcmaddcsh.asm",
  "option": "--bits 64 -w-ea-absolute -w-implicit-abs-deprecated -I./travis/insns/vfcmaddcsh/",
  "target": [
   { "output": "vfcmaddcsh.bin64", "match": "vfcmaddcsh.bin64.t" }
  ]
 }
]
